pyembeddings/__init__.py
pyembeddings/collection.py
pyembeddings/database.py
pyembeddings/generator.py
pyembeddings-0.1.2.dist-info/METADATA
pyembeddings-0.1.2.dist-info/WHEEL
pyembeddings-0.1.2.dist-info/top_level.txt
pyembeddings-0.1.2.dist-info/RECORD
